{
  "list":[
    "誕生日",
    "【おかえり、ギター】浅倉透",
    "Morning",
    "【ハウ・アー・UFO】浅倉透",
    "【かっとばし党の逆襲】浅倉透",
    "ファン感謝祭編",
    "G.R.A.D.編",
    "【がんばれ！ノロマ号】浅倉透",
    "【10個、光】浅倉透",
    "W.I.N.G.編",
    "【faaaar】浅倉透",
    "【途方もない午後】浅倉透",
    "【つづく、】浅倉透",
    "【pooool】浅倉 透",
    "【２８３プロのヒナ】浅倉透",
    "节日剧情",
    "【まわるものについて】",
    "Landing Point編"
  ],
  "details":{
    "誕生日":[
      "【浅倉 透】 誕生日ミニコミュ①.csv"
    ],
    "【おかえり、ギター】浅倉透":[
      "おまえのなまえ.csv",
      "おまえのおと.csv",
      "捕.csv"
    ],
    "Morning":[
      "produce_communications_102000100061.csv",
      "produce_communications_102000100071.csv",
      "produce_communications_102000100121.csv",
      "produce_communications_102000100091.csv",
      "produce_communications_102000100111.csv",
      "produce_communications_102000100131.csv",
      "produce_communications_102000100051.csv",
      "produce_communications_102000100101.csv",
      "produce_communications_102000100021.csv",
      "produce_communications_102000100141.csv",
      "produce_communications_102000100011.csv",
      "produce_communications_102000100081.csv",
      "produce_communications_102000100031.csv",
      "produce_communications_102000100151.csv",
      "produce_communications_102000100041.csv"
    ],
    "【ハウ・アー・UFO】浅倉透":[
      "たぶん絶対、おそらく.csv",
      "ろーかる銀河.csv",
      "うわの宙.csv"
    ],
    "【かっとばし党の逆襲】浅倉透":[
      "おもいこんだら.csv",
      "われらはつくるわれらのりゆう.csv"
    ],
    "ファン感謝祭編":[
      "リハーサル前.csv",
      "遅刻ならず.csv",
      "感謝祭本番前.csv",
      "遅刻.csv",
      "リハーサル後.csv"
    ],
    "G.R.A.D.編":[
      "息したいだけ.csv",
      "予選前コミュ.csv",
      "决赛后剧情 胜利.csv",
      "决赛前剧情.csv",
      "G.R.A.D.淘汰剧情①.csv",
      "决赛后剧情　失败②.csv",
      "敗者復活前コミュ.csv",
      "决赛后剧情　失败①.csv",
      "予選後コミュ 胜利.csv",
      "敗者復活後コミュ　胜利.csv",
      "G.R.A.D.淘汰剧情②前.csv",
      "敗者復活後コミュ　失败.csv",
      "息してるだけ.csv",
      "G.R.A.D.淘汰剧情②後.csv",
      "携帯が鳴ってる.csv",
      "鼓動 .csv",
      "泥の中.csv",
      "どうしたいのかとか、聞かれても.csv",
      "予選後コミュ　失败.csv"
    ],
    "【がんばれ！ノロマ号】浅倉透":[
      "かんぱい.csv",
      "鳥.csv",
      "いつか忘れること.csv"
    ],
    "【10個、光】浅倉透":[
      "２こめ.csv",
      "３こめ.csv",
      "１こめ.csv",
      "いつか.csv",
      "４こめ.csv"
    ],
    "W.I.N.G.編":[
      "produce_events_102000101.csv",
      "produce_communication_auditions_502000100011.csv",
      "produce_events_702000101.csv",
      "produce_communication_auditions_502000100022.csv",
      "produce_events_102000103.csv",
      "produce_events_602000104.csv",
      "produce_events_102000002.csv",
      "produce_communication_cheers_402000100012.csv",
      "produce_events_702000107.csv",
      "produce_events_602000103.csv",
      "produce_events_102000102.csv",
      "produce_events_702000103.csv",
      "produce_events_702000105.csv",
      "produce_events_702000104.csv",
      "produce_events_602000106.csv",
      "produce_events_702000108.csv",
      "produce_events_602000102.csv",
      "produce_events_702000102.csv",
      "produce_communication_cheers_402000100022.csv",
      "produce_communication_auditions_502000100021.csv",
      "produce_events_602000107.csv",
      "produce_communication_cheers_402000100021.csv",
      "produce_communication_cheers_402000100013.csv",
      "produce_events_602000109.csv",
      "produce_communication_cheers_402000100023.csv",
      "produce_events_702000106.csv",
      "produce_events_602000101.csv",
      "produce_communication_auditions_502000100012.csv",
      "produce_events_102000105.csv",
      "produce_communication_cheers_402000100011.csv",
      "produce_events_102000104.csv"
    ],
    "【faaaar】浅倉透":[
      "so easy.csv",
      "so smooth.csv"
    ],
    "【途方もない午後】浅倉透":[
      "所感：頑張ろうな.csv",
      "所感：.csv",
      "午後１.csv",
      "午後３.csv",
      "午後２.csv"
    ],
    "【つづく、】浅倉透":[
      "おぼえて　よ.csv",
      "　わる時間.csv",
      "日誌出　ます.csv",
      "見　ことある.csv",
      "リバ　ス.csv"
    ],
    "【pooool】浅倉 透":[
      "泳げばとうとし.csv",
      "虫たちの夜.csv",
      "プール・フール.csv"
    ],
    "【２８３プロのヒナ】浅倉透":[
      "produce_events_302000201.csv",
      "produce_events_302000202.csv"
    ],
    "节日剧情":[
      "圣诞节"
    ],
    "【まわるものについて】":[
      "2.csv",
      "1.csv"
    ],
    "Landing Point編":[
      "07ライブ2曲目前コミュ《個人》.csv",
      "08ライブ3曲目前コミュ《個人》.csv",
      "09ライブ後コミュ《個人》　大成功.csv",
      "99ラスト.csv",
      "01そんなふうに終わるね.csv",
      "02街はつづく、人生みたいに.csv",
      "05キッチンできみは火薬をまぜる.csv",
      "04火.csv",
      "03オエイシス、イエー.csv",
      "06ライブ1曲目前コミュ《個人》.csv"
    ]
  }
}